recommender/__init__.py
recommender/api.py
music_recommender-1.0.5.dist-info/METADATA
music_recommender-1.0.5.dist-info/WHEEL
music_recommender-1.0.5.dist-info/top_level.txt
music_recommender-1.0.5.dist-info/RECORD
