Metadata-Version: 2.1
Name: music-recommender
Version: 1.0.5
Summary: A Python client for the Spotify Recommendations API.
Home-page: https://github.com/AnthonyBloomer/recommender
Author: Anthony Bloomer
Author-email: ant0@protonmail.ch
License: MIT
Keywords: spotify,api,music recommendations,music recommender
Platform: UNKNOWN
Classifier: Intended Audience :: Developers
Classifier: License :: OSI Approved :: MIT License
Classifier: Topic :: Software Development :: Libraries
Classifier: Programming Language :: Python
Classifier: Programming Language :: Python :: 2.7
Classifier: Programming Language :: Python :: 3
Classifier: Programming Language :: Python :: 3.3
Classifier: Programming Language :: Python :: 3.4
Classifier: Programming Language :: Python :: 3.5
Classifier: Programming Language :: Python :: 3.6
Requires-Dist: requests
Requires-Dist: six
